input_analyzor/__init__.py
input_analyzor/input_analyzor.py
plant_visualization-0.0.2.dist-info/LICENSE
plant_visualization-0.0.2.dist-info/METADATA
plant_visualization-0.0.2.dist-info/WHEEL
plant_visualization-0.0.2.dist-info/top_level.txt
plant_visualization-0.0.2.dist-info/RECORD
