Metadata-Version: 2.1
Name: plant-visualization
Version: 0.0.2
Summary: Arena mine model input analyzor, working with excel input workbook 116D
Home-page: https://github.riotinto.org/IOps-Strategy-Simulation-Modelling/Input-Analyzor
Author: Alex Z
Author-email: alexchunggh@gmail.com
License: UNKNOWN
Platform: UNKNOWN
Classifier: Programming Language :: Python :: 3
Classifier: License :: OSI Approved :: MIT License
Classifier: Operating System :: OS Independent
Requires-Python: >=3.6
